[
  {
    "drawNumber": 1555,
    "winningNumbers": [
      36,
      19,
      17,
      3,
      41,
      11,
      32
    ],
    "specialNumbers": [
      34,
      6,
      22
    ],
    "drawDate": "05/12/2023"
  },
  {
    "drawNumber": 1556,
    "winningNumbers": [
      6,
      44,
      30,
      42,
      19,
      39,
      47
    ],
    "specialNumbers": [
      8,
      46,
      33
    ],
    "drawDate": "12/12/2023"
  },
  {
    "drawNumber": 1557,
    "winningNumbers": [
      18,
      12,
      47,
      25,
      37,
      43,
      40
    ],
    "specialNumbers": [
      28,
      30,
      32
    ],
    "drawDate": "19/12/2023"
  },
  {
    "drawNumber": 1558,
    "winningNumbers": [
      17,
      44,
      22,
      42,
      31,
      24,
      28
    ],
    "specialNumbers": [
      3,
      16,
      39
    ],
    "drawDate": "26/12/2023"
  },
  {
    "drawNumber": 1559,
    "winningNumbers": [
      36,
      44,
      3,
      46,
      24,
      21,
      30
    ],
    "specialNumbers": [
      37,
      18,
      31
    ],
    "drawDate": "02/01/2024"
  },
  {
    "drawNumber": 1560,
    "winningNumbers": [
      5,
      6,
      42,
      38,
      21,
      25,
      22
    ],
    "specialNumbers": [
      36,
      44,
      16
    ],
    "drawDate": "09/01/2024"
  },
  {
    "drawNumber": 1561,
    "winningNumbers": [
      17,
      37,
      4,
      29,
      9,
      24,
      47
    ],
    "specialNumbers": [
      20,
      27,
      14
    ],
    "drawDate": "16/01/2024"
  },
  {
    "drawNumber": 1562,
    "winningNumbers": [
      15,
      26,
      2,
      18,
      44,
      20,
      27
    ],
    "specialNumbers": [
      10,
      1,
      42
    ],
    "drawDate": "23/01/2024"
  },
  {
    "drawNumber": 1563,
    "winningNumbers": [
      27,
      4,
      34,
      29,
      28,
      25,
      20
    ],
    "specialNumbers": [
      38,
      26,
      12
    ],
    "drawDate": "30/01/2024"
  },
  {
    "drawNumber": 1564,
    "winningNumbers": [
      3,
      10,
      13,
      20,
      31,
      38,
      39
    ],
    "specialNumbers": [
      12,
      33,
      41
    ],
    "drawDate": "06/02/2024"
  }
]